{
	"ImportPath": "github.com/briansimoni/go-rest-example",
	"GoVersion": "go1.6",
	"GodepVersion": "v74",
	"Deps": [
		{
			"ImportPath": "github.com/emicklei/go-restful",
			"Comment": "v1.2-79-g89ef8af",
			"Rev": "89ef8af493ab468a45a42bb0d89a06fccdd2fb22"
		},
		{
			"ImportPath": "github.com/emicklei/go-restful/log",
			"Comment": "v1.2-79-g89ef8af",
			"Rev": "89ef8af493ab468a45a42bb0d89a06fccdd2fb22"
		},
		{
			"ImportPath": "github.com/nu7hatch/gouuid",
			"Rev": "179d4d0c4d8d407a32af483c2354df1d2c91e6c3"
		}
	]
}
